nldsl/__init__.py
nldsl/docs.py
nldsl/pandas_extension.py
nldsl/spark_extension.py
nldsl/core/__init__.py
nldsl/core/codegen.py
nldsl/core/exceptions.py
nldsl/core/external.py
nldsl/core/internal.py
nldsl/core/rules.py
nldsl/core/types.py
nldsl/core/utils.py
nldsl/core/grammar/expr_grammar.tx
nldsl/core/grammar/grammar.tx
nldsl-0.15.4.data/scripts/nldsl-compile.py
nldsl-0.15.4.dist-info/LICENSE.txt
nldsl-0.15.4.dist-info/METADATA
nldsl-0.15.4.dist-info/WHEEL
nldsl-0.15.4.dist-info/top_level.txt
nldsl-0.15.4.dist-info/RECORD
