Metadata-Version: 1.2
Name: nldsl
Version: 0.15.4
Summary: A DSL for data science with a syntax similar to a natural language.
Home-page: https://gitlab.com/Einhornstyle/nldsl
Author: Kevin Kiefer
Author-email: abc.kiefer@gmail.com
License: UNKNOWN
Project-URL: Documentation, https://einhornstyle.gitlab.io/nldsl/
Platform: UNKNOWN
Classifier: Development Status :: 5 - Production/Stable
Classifier: License :: Free for non-commercial use
Classifier: Natural Language :: English
Classifier: Programming Language :: Python :: 3.4
Classifier: Programming Language :: Python :: 3 :: Only
Classifier: Topic :: Software Development :: Code Generators
Classifier: Topic :: Software Development :: Compilers
Requires-Python: >=3.4
